django_donations-1.2.0.dist-info/METADATA
django_donations-1.2.0.dist-info/RECORD
django_donations-1.2.0.dist-info/WHEEL
django_donations-1.2.0.dist-info/top_level.txt
donations/__init__.py
donations/admin.py
donations/app_settings.py
donations/apps.py
donations/forms.py
donations/models.py
donations/serializers.py
donations/urls.py
donations/views.py
donations/migrations/0001_squashed_0002_auto_20170127_1004.py
donations/migrations/0002_auto_20170919_0800.py
donations/migrations/0003_auto_20180618_0458.py
donations/migrations/__init__.py
donations/providers/__init__.py
donations/providers/base.py
donations/providers/just_giving.py
