Metadata-Version: 1.1
Name: django-donations
Version: 1.2.0
Summary: Reusable django app to receive & track donations on charitable sites
Home-page: https://github.com/founders4schools/django-donations
Author: Andrew Miller
Author-email: dev@founders4schools.org.uk
License: BSD
Keywords: django-donations
Platform: UNKNOWN
Classifier: Development Status :: 5 - Production/Stable
Classifier: Framework :: Django
Classifier: Framework :: Django :: 1.11
Classifier: Framework :: Django :: 2.0
Classifier: Intended Audience :: Developers
Classifier: License :: OSI Approved :: BSD License
Classifier: Natural Language :: English
Classifier: Programming Language :: Python :: 3
Classifier: Programming Language :: Python :: 3.5
Classifier: Programming Language :: Python :: 3.6
Classifier: Programming Language :: Python :: 3.7
